ylcli/__init__.py
ylcli/cli.py
ylcli/libs.py
ylcli/template/Pipfile
ylcli/template/YunDou.py
ylcli/template/app/__init__.py
ylcli/template/app/app.py
ylcli/template/app/api/__init__.py
ylcli/template/app/api/v1/Greeting.py
ylcli/template/app/api/v1/__init__.py
ylcli/template/app/config/secure.py
ylcli/template/app/config/setting.py
ylcli/template/app/libs/__init__.py
ylcli/template/app/libs/error.py
ylcli/template/app/libs/error_code.py
ylcli/template/app/libs/redPrint.py
ylcli/template/app/libs/util.py
ylcli/template/app/models/ExcuteFun.py
ylcli/template/app/models/OperateTab.py
ylcli/template/app/models/ReflectView.py
ylcli/template/app/models/__init__.py
ylcli/template/app/models/base.py
yl_app-0.0.3.dist-info/LICENSE
yl_app-0.0.3.dist-info/METADATA
yl_app-0.0.3.dist-info/WHEEL
yl_app-0.0.3.dist-info/entry_points.txt
yl_app-0.0.3.dist-info/top_level.txt
yl_app-0.0.3.dist-info/RECORD
