Metadata-Version: 2.1
Name: yl-app
Version: 0.0.3
Summary: a tiny cli to generate flask project
Home-page: https://gitee.com/ytxgyl/yundou-cli
Author: 芸荳
Author-email: yl20181003@gmail.com
License: UNKNOWN
Platform: UNKNOWN
Classifier: Programming Language :: Python :: 3.7
Classifier: License :: OSI Approved :: MIT License
Classifier: Operating System :: OS Independent
